glowgreen/__init__.py
glowgreen/clearance.py
glowgreen/close_contact.py
glowgreen-0.1.1.dist-info/METADATA
glowgreen-0.1.1.dist-info/WHEEL
glowgreen-0.1.1.dist-info/licenses/LICENSE
glowgreen-0.1.1.dist-info/RECORD
