Metadata-Version: 2.4
Name: glowgreen
Version: 0.1.1
Summary: Radiation dose from close contact patterns with radioactive patients.
Project-URL: Homepage, https://github.com/SAMI-Medical-Physics/glowgreen
Project-URL: Bug Tracker, https://github.com/SAMI-Medical-Physics/glowgreen/issues
Project-URL: Documentation, https://glowgreen.readthedocs.io
Project-URL: Changelog, https://github.com/SAMI-Medical-Physics/glowgreen/CHANGELOG.md
Author: Jake Forster, Erin Lukas
License: MIT
License-File: LICENSE
Classifier: License :: OSI Approved :: MIT License
Classifier: Operating System :: OS Independent
Classifier: Programming Language :: Python :: 3
Classifier: Topic :: Scientific/Engineering :: Medical Science Apps.
Requires-Python: >=3.9
Requires-Dist: matplotlib<4,>=3.5.0
Requires-Dist: numpy<3,>=1.21.4
Requires-Dist: pandas<3,>=1.3.4
Requires-Dist: scipy<2,>=1.7.3
